GEOparse/GEOTypes.py
GEOparse/GEOparse.py
GEOparse/__init__.py
GEOparse/downloader.py
GEOparse/logger.py
GEOparse/sra_downloader.py
GEOparse/utils.py
GEOparse-2.0.4.data/scripts/geo2fastq
GEOparse-2.0.4.dist-info/AUTHORS.rst
GEOparse-2.0.4.dist-info/LICENSE
GEOparse-2.0.4.dist-info/METADATA
GEOparse-2.0.4.dist-info/WHEEL
GEOparse-2.0.4.dist-info/top_level.txt
GEOparse-2.0.4.dist-info/RECORD
