Metadata-Version: 2.1
Name: GEOparse
Version: 2.0.4
Summary: Python library to access Gene Expression Omnibus Database (GEO)
Home-page: https://github.com/guma44/GEOparse
Author: Rafal Gumienny
Author-email: guma44@gmail.com
License: BSD
Project-URL: Documentation, https://geoparse.readthedocs.io/
Project-URL: Changelog, https://geoparse.readthedocs.io/en/latest/history.html
Project-URL: Issue Tracker, https://github.com/guma44/GEOparse/issues
Keywords: GEOparse,GEO,Gene Expression Omnibus,Bioinformatics,Microarray
Classifier: Development Status :: 5 - Production/Stable
Classifier: Intended Audience :: Developers
Classifier: License :: OSI Approved :: BSD License
Classifier: Natural Language :: English
Classifier: Programming Language :: Python :: 3.5
Classifier: Programming Language :: Python :: 3.6
Classifier: Programming Language :: Python :: 3.7
Requires-Python: >3.5.0
License-File: LICENSE
License-File: AUTHORS.rst
Requires-Dist: numpy>=1.7
Requires-Dist: pandas>=0.17
Requires-Dist: requests>=2.21.0
Requires-Dist: tqdm>=4.31.1
